{"backbone": "seresnet101", "keyponits": 17, "se_ratio": 16, "first_conv": 11, "residual": [256, 512, 1024, 2048], "channels": {"1": [[7, 9], [10, 11], [10, 6]], "2": [[18, 21], [24, 21], [24, 18], [28, 24]], "3": [[43, 51], [52, 41], [55, 39], [43, 47], [59, 44], [49, 52], [46, 39], [46, 54], [36, 58], [47, 49], [52, 45], [47, 53], [50, 58], [58, 49], [50, 49], [49, 54], [58, 56], [49, 66], [55, 59], [56, 42], [50, 43], [59, 52], [48, 59]], "4": [[105, 116], [120, 120], [130, 129]]}, "head_type": "pixel_shuffle", "head_channel": [288, 12]}